de/setup_project.py
de_setup_project-0.2.5.data/data/.gitignore
de_setup_project-0.2.5.data/data/.gitlab-ci.yml
de_setup_project-0.2.5.data/data/CONTRIBUTING.rst
de_setup_project-0.2.5.data/data/LICENSE.md
de_setup_project-0.2.5.data/data/README.md
de_setup_project-0.2.5.data/data/SECURITY.md
de_setup_project-0.2.5.data/data/coverage.svg
de_setup_project-0.2.5.data/data/coverage.txt
de_setup_project-0.2.5.data/data/dev_requirements.txt
de_setup_project-0.2.5.data/data/requirements.txt
de_setup_project-0.2.5.data/data/setup.py
de_setup_project-0.2.5.dist-info/LICENSE.md
de_setup_project-0.2.5.dist-info/METADATA
de_setup_project-0.2.5.dist-info/WHEEL
de_setup_project-0.2.5.dist-info/top_level.txt
de_setup_project-0.2.5.dist-info/zip-safe
de_setup_project-0.2.5.dist-info/RECORD
